{
  "$schema": "https://raw.githubusercontent.com/spdx/spdx-spec/v2.2.1/schemas/spdx-schema.json",
  "spdxVersion": "SPDX-2.2",
  "dataLicense": "CC0-1.0",
  "SPDXID": "SPDXRef-DOCUMENT",
  "documentNamespace": "https://spdx.org/spdxdocs/boost-filesystem-arm64-osx-1.82.0#2-5ec9a746-40d9-487a-985c-d995b16f58b0",
  "name": "boost-filesystem:arm64-osx@1.82.0#2 0e5946579860049a6bdad8ae3436e34a1ce1b3dbcb0605436a67bb895f2b76c1",
  "creationInfo": {
    "creators": [
      "Tool: vcpkg-814b7ec837b59f1c8778f72351c1dd7605983cd2"
    ],
    "created": "2023-07-25T12:46:48Z"
  },
  "relationships": [
    {
      "spdxElementId": "SPDXRef-port",
      "relationshipType": "GENERATES",
      "relatedSpdxElement": "SPDXRef-binary"
    },
    {
      "spdxElementId": "SPDXRef-port",
      "relationshipType": "CONTAINS",
      "relatedSpdxElement": "SPDXRef-file-0"
    },
    {
      "spdxElementId": "SPDXRef-port",
      "relationshipType": "CONTAINS",
      "relatedSpdxElement": "SPDXRef-file-1"
    },
    {
      "spdxElementId": "SPDXRef-binary",
      "relationshipType": "GENERATED_FROM",
      "relatedSpdxElement": "SPDXRef-port"
    },
    {
      "spdxElementId": "SPDXRef-file-0",
      "relationshipType": "CONTAINED_BY",
      "relatedSpdxElement": "SPDXRef-port"
    },
    {
      "spdxElementId": "SPDXRef-file-1",
      "relationshipType": "CONTAINED_BY",
      "relatedSpdxElement": "SPDXRef-port"
    },
    {
      "spdxElementId": "SPDXRef-file-1",
      "relationshipType": "DEPENDENCY_MANIFEST_OF",
      "relatedSpdxElement": "SPDXRef-port"
    }
  ],
  "packages": [
    {
      "name": "boost-filesystem",
      "SPDXID": "SPDXRef-port",
      "versionInfo": "1.82.0#2",
      "downloadLocation": "git+https://github.com/Microsoft/vcpkg#ports/boost-filesystem",
      "homepage": "https://github.com/boostorg/filesystem",
      "licenseConcluded": "BSL-1.0",
      "licenseDeclared": "NOASSERTION",
      "copyrightText": "NOASSERTION",
      "description": "Boost filesystem module",
      "comment": "This is the port (recipe) consumed by vcpkg."
    },
    {
      "name": "boost-filesystem:arm64-osx",
      "SPDXID": "SPDXRef-binary",
      "versionInfo": "0e5946579860049a6bdad8ae3436e34a1ce1b3dbcb0605436a67bb895f2b76c1",
      "downloadLocation": "NONE",
      "licenseConcluded": "BSL-1.0",
      "licenseDeclared": "NOASSERTION",
      "copyrightText": "NOASSERTION",
      "comment": "This is a binary package built by vcpkg."
    },
    {
      "SPDXID": "SPDXRef-resource-1",
      "name": "boostorg/filesystem",
      "downloadLocation": "git+https://github.com/boostorg/filesystem@boost-1.82.0",
      "licenseConcluded": "NOASSERTION",
      "licenseDeclared": "NOASSERTION",
      "copyrightText": "NOASSERTION",
      "checksums": [
        {
          "algorithm": "SHA512",
          "checksumValue": "53141484dbfc0ee399333eaadc87cb5fe077d0be8dbfb69c6a9c4545d254e894f0f0f7fb16f7de72c344f91ac29c2769125324ad2363b36b7a82bc4651472501"
        }
      ]
    }
  ],
  "files": [
    {
      "fileName": "./portfile.cmake",
      "SPDXID": "SPDXRef-file-0",
      "checksums": [
        {
          "algorithm": "SHA256",
          "checksumValue": "f1a30cbf87cc97ea4809096ff80db1c0d27a4c8f5b4e330e28f7594c43443c26"
        }
      ],
      "licenseConcluded": "NOASSERTION",
      "copyrightText": "NOASSERTION"
    },
    {
      "fileName": "./vcpkg.json",
      "SPDXID": "SPDXRef-file-1",
      "checksums": [
        {
          "algorithm": "SHA256",
          "checksumValue": "86691e28088cc8b11cc6e8838cbb3edf3b08596a50476c3643b835c6ed217f33"
        }
      ],
      "licenseConcluded": "NOASSERTION",
      "copyrightText": "NOASSERTION"
    }
  ]
}
